[
    {
        "name": "JENNIFER",
        "last": "ESCALANTE FONSECA",
        "dni": 1052084156,
        "email": "jennieef12@hotmail.com",
        "phone": 3126000783
    },
    {
        "name": "HERNANDO",
        "last": "ACEVEDO",
        "dni": 92260871,
        "email": "severohernando77@gmail.com",
        "phone": 3006834340
    },
    {
        "name": "YAIR JOSÉ",
        "last": "RÍOS DOMÍNGUEZ",
        "dni": 1102864884,
        "email": "yario04@hotmail.com",
        "phone": 0
    },
    {
        "name": "JUAN CARLOS",
        "last": "FIGUEROA VERGARA",
        "dni": 3838230,
        "email": "juan_figueroavergara@hotmail.com",
        "phone": 3007119309
    },
    {
        "name": "EFRAÍN ALBERTOH",
        "last": "BUITRAGO TAPIA",
        "dni": 92530090,
        "email": "efrabu47@gmail.com",
        "phone": 0
    },
    {
        "name": "KAREN MILENA",
        "last": "MERCADO MARTINEZ",
        "dni": 1102812509,
        "email": "kamer_2220@hotmail.com",
        "phone": 0
    },
    {
        "name": "CRISTIAN JAVIER",
        "last": "BLANQUICETHTAMARA",
        "dni": 1102863528,
        "email": "cristian.blanq@gmail.com",
        "phone": 0
    },
    {
        "name": "ENOC MESAC",
        "last": "ROMERO GONZÁLEZ",
        "dni": 92642220,
        "email": "enocromero@gmail.com",
        "phone": 0
    },
    {
        "name": "LILIANA PAOLA",
        "last": "DIAZ TORRES",
        "dni": 64699484,
        "email": "oapil7546@hotmail.com",
        "phone": 0
    },
    {
        "name": "SUMAYA",
        "last": "ESTRADA CURE",
        "dni": 23175669,
        "email": "sestradacure@hotmail.com",
        "phone": 3013712737
    },
    {
        "name": "AGUSTÍN SEVERIANO",
        "last": "ROMERO SANTOS",
        "dni": 92553287,
        "email": "rs_agustinromero@hotmalli.com",
        "phone": 0
    },
    {
        "name": "DAINER",
        "last": "PEREZ NAVARRO",
        "dni": 1102855689,
        "email": "janperez1992@hotmail.com",
        "phone": 3206580524
    },
    {
        "name": "LILA ROSA",
        "last": "AGUAS NAVARRO",
        "dni": 1102874064,
        "email": "lilaaguas35@gmail.com",
        "phone": 3205508262
    },
    {
        "name": "CARLOS ANDRES",
        "last": "PEREZ NAZAR",
        "dni": 92558188,
        "email": "carlospereznazar@hotmail.com",
        "phone": 0
    },
    {
        "name": "ALBEIRO RAMÓN",
        "last": "CONTRERAS AMADOR",
        "dni": 9314406,
        "email": "albeirocontreras@yahoo.es",
        "phone": 3103967577
    },
    {
        "name": "LINA MARÍA",
        "last": "ANAYA ROMERO",
        "dni": 1100629481,
        "email": "linaanaya44@gmail.com",
        "phone": 3105952321
    },
    {
        "name": "EDWIN JOSÉ",
        "last": "BELLO JULIO",
        "dni": 92448380,
        "email": "edwinjosebellojulio@gmail.com",
        "phone": 3014545952
    },
    {
        "name": "NEVIS",
        "last": "GARCIA PEREZ",
        "dni": 1102880792,
        "email": "Garcianevis35@gmail.com",
        "phone": 0
    },
    {
        "name": "MAURA CAROLINA",
        "last": "GARCÍA SIVENTRIZ",
        "dni": 1101818219,
        "email": "arqmauracarolina@gmail.com",
        "phone": 0
    }
]
